diceman/__init__.py
diceman-0.1.1.dist-info/LICENSE
diceman-0.1.1.dist-info/METADATA
diceman-0.1.1.dist-info/WHEEL
diceman-0.1.1.dist-info/top_level.txt
diceman-0.1.1.dist-info/RECORD
